nimbaldetach/__init__.py
nimbaldetach/nimbaldetach.py
nimbaldetach-1.0.3.dist-info/LICENSE
nimbaldetach-1.0.3.dist-info/METADATA
nimbaldetach-1.0.3.dist-info/WHEEL
nimbaldetach-1.0.3.dist-info/top_level.txt
nimbaldetach-1.0.3.dist-info/RECORD
