Metadata-Version: 2.1
Name: nimbaldetach
Version: 1.0.3
Summary: DETACH (Device Temperature and Acceleration Change) algorithm for detecting non-wear from raw accelerometer data.
Home-page: https://github.com/nimbal/nimbaldetach
Author: Adam Vert
Author-email: vertadam@gmail.com
Classifier: Programming Language :: Python :: 3
Classifier: License :: OSI Approved :: MIT License
Classifier: Operating System :: OS Independent
Requires-Python: >=3.9
License-File: LICENSE
Requires-Dist: numpy >=1.22.1
Requires-Dist: pandas >=1.4.0
Requires-Dist: scipy >=1.7.3
